{"cameraMode":{"drawMode":0,"name":"Shaded","section":"Shading Mode"},"sceneLighting":true,"audioPlay":false,"sceneViewState":{"m_AlwaysRefresh":false,"showFog":true,"showSkybox":true,"showFlares":true,"showImageEffects":true,"showParticleSystems":true,"showVisualEffectGraphs":true,"m_FxEnabled":true},"in2DMode":false,"pivot":{"x":11.667028427124024,"y":-34.618595123291019,"z":116.574951171875},"rotation":{"x":-0.1832227110862732,"y":-0.057419586926698688,"z":0.010028664954006672,"w":-0.9813761711120606},"size":78.8951644897461,"orthographic":false}